doinfo/__init__.py
doinfo/doi.py
doinfo-1.3.dist-info/LICENSE
doinfo-1.3.dist-info/METADATA
doinfo-1.3.dist-info/WHEEL
doinfo-1.3.dist-info/top_level.txt
doinfo-1.3.dist-info/RECORD
